WindowsBianchengRumenWindowsChengxusheji1XiaoshiRumenjiaocheng/README.md
WindowsBianchengRumenWindowsChengxusheji1XiaoshiRumenjiaocheng/__init__.py
WindowsBianchengRumenWindowsChengxusheji1XiaoshiRumenjiaocheng/__main__.py
WindowsBianchengRumenWindowsChengxusheji1XiaoshiRumenjiaocheng/file.epub
WindowsBianchengRumenWindowsChengxusheji1XiaoshiRumenjiaocheng/index.html
WindowsBianchengRumenWindowsChengxusheji1XiaoshiRumenjiaocheng/css/__init__.py
WindowsBianchengRumenWindowsChengxusheji1XiaoshiRumenjiaocheng/css/annotations.css
WindowsBianchengRumenWindowsChengxusheji1XiaoshiRumenjiaocheng/css/main.css
WindowsBianchengRumenWindowsChengxusheji1XiaoshiRumenjiaocheng/css/normalize.css
WindowsBianchengRumenWindowsChengxusheji1XiaoshiRumenjiaocheng/css/popup.css
WindowsBianchengRumenWindowsChengxusheji1XiaoshiRumenjiaocheng/font/__init__.py
WindowsBianchengRumenWindowsChengxusheji1XiaoshiRumenjiaocheng/font/fontello.eot
WindowsBianchengRumenWindowsChengxusheji1XiaoshiRumenjiaocheng/font/fontello.svg
WindowsBianchengRumenWindowsChengxusheji1XiaoshiRumenjiaocheng/font/fontello.ttf
WindowsBianchengRumenWindowsChengxusheji1XiaoshiRumenjiaocheng/font/fontello.woff
WindowsBianchengRumenWindowsChengxusheji1XiaoshiRumenjiaocheng/img/__init__.py
WindowsBianchengRumenWindowsChengxusheji1XiaoshiRumenjiaocheng/img/annotator-glyph-sprite.png
WindowsBianchengRumenWindowsChengxusheji1XiaoshiRumenjiaocheng/img/annotator-icon-sprite.png
WindowsBianchengRumenWindowsChengxusheji1XiaoshiRumenjiaocheng/img/apple-touch-icon.png
WindowsBianchengRumenWindowsChengxusheji1XiaoshiRumenjiaocheng/img/cancelfullscreen.png
WindowsBianchengRumenWindowsChengxusheji1XiaoshiRumenjiaocheng/img/close.png
WindowsBianchengRumenWindowsChengxusheji1XiaoshiRumenjiaocheng/img/fullscreen.png
WindowsBianchengRumenWindowsChengxusheji1XiaoshiRumenjiaocheng/img/loader.gif
WindowsBianchengRumenWindowsChengxusheji1XiaoshiRumenjiaocheng/img/menu-icon.png
windows_biancheng_rumen_windows_chengxusheji_1_xiaoshi_rumenjiaocheng-2024.3.2.0.dist-info/METADATA
windows_biancheng_rumen_windows_chengxusheji_1_xiaoshi_rumenjiaocheng-2024.3.2.0.dist-info/WHEEL
windows_biancheng_rumen_windows_chengxusheji_1_xiaoshi_rumenjiaocheng-2024.3.2.0.dist-info/entry_points.txt
windows_biancheng_rumen_windows_chengxusheji_1_xiaoshi_rumenjiaocheng-2024.3.2.0.dist-info/top_level.txt
windows_biancheng_rumen_windows_chengxusheji_1_xiaoshi_rumenjiaocheng-2024.3.2.0.dist-info/RECORD
